external_ip/__init__.py
external_ip/__main__.py
nullent1ty_external_ip-1.0.2.dist-info/LICENSE
nullent1ty_external_ip-1.0.2.dist-info/METADATA
nullent1ty_external_ip-1.0.2.dist-info/WHEEL
nullent1ty_external_ip-1.0.2.dist-info/top_level.txt
nullent1ty_external_ip-1.0.2.dist-info/RECORD
