Metadata-Version: 2.1
Name: nullent1ty-external-ip
Version: 1.0.2
Summary: Retrieve your external IPv4 address.
Home-page: https://github.com/NullEnt1ty/external-ip
Author: Dominique Mattern
Author-email: dominique@mattern.dev
License: MIT
Platform: UNKNOWN
Classifier: Programming Language :: Python :: 3
Classifier: License :: OSI Approved :: MIT License
Classifier: Operating System :: OS Independent
Requires-Dist: urllib3 (==1.25.9)
